ru_word2number/w2n.py
ru_word2number-1.1.dist-info/LICENSE.txt
ru_word2number-1.1.dist-info/METADATA
ru_word2number-1.1.dist-info/WHEEL
ru_word2number-1.1.dist-info/top_level.txt
ru_word2number-1.1.dist-info/RECORD
