Metadata-Version: 2.1
Name: ru-word2number
Version: 1.1
Summary: Convert russian number words eg. триста сорок два to numbers (342).
Home-page: https://github.com/Oknolaz/Russian_w2n
Author: Oknolaz
Author-email: oknolaz.freedom@protonmail.com
License: The MIT License (MIT)
